decaptcha/__init__.py
decaptcha/apps.py
decaptcha/challenges.py
decaptcha/models.py
decaptcha/settings.py
decaptcha/tests.py
decaptcha/urls.py
decaptcha/utils.py
decaptcha/validators.py
decaptcha/views.py
django_easy_captcha-1.1.dist-info/LICENSE
django_easy_captcha-1.1.dist-info/METADATA
django_easy_captcha-1.1.dist-info/WHEEL
django_easy_captcha-1.1.dist-info/top_level.txt
django_easy_captcha-1.1.dist-info/RECORD
